kitsai/__init__.py
kitsai/token.py
kitsai/tts/create_tts.py
kitsai/tts/fetch_tts.py
kitsai/tts/fetch_tts_by_id.py
kitsai/vocal_separations/create_vocal_separation.py
kitsai/vocal_separations/fetch_vocal_separation_by_id.py
kitsai/vocal_separations/fetch_vocal_separations.py
kitsai/voice_conversions/create_voice_conversion.py
kitsai/voice_conversions/fetch_voice_conversion_by_id.py
kitsai/voice_conversions/fetch_voice_conversions.py
kitsai/voice_models/fetch_voice_model_by_id.py
kitsai/voice_models/fetch_voice_models.py
kitsai-0.0.3.dist-info/LICENSE
kitsai-0.0.3.dist-info/METADATA
kitsai-0.0.3.dist-info/WHEEL
kitsai-0.0.3.dist-info/top_level.txt
kitsai-0.0.3.dist-info/RECORD
