Metadata-Version: 2.1
Name: kitsai
Version: 0.0.3
Summary: Unofficial package to easily interact with the Kits.AI API
Home-page: https://github.com/blaise-tk/kitsai
Author: Blaise
Author-email: iahispano0@gmail.com
License: Attribution-NonCommercial 4.0 International
Keywords: python,audio,vc,ai,rvc,kits
Classifier: Intended Audience :: Developers
Classifier: Programming Language :: Python :: 3
Classifier: Operating System :: MacOS :: MacOS X
Classifier: Operating System :: Microsoft :: Windows :: Windows 10
Classifier: Operating System :: POSIX :: Linux
License-File: LICENSE
